shipyard_api/__init__.py
shipyard_api/cli/authtest.py
shipyard_api/cli/get_logs.py
shipyard_api/cli/trigger_fleet.py
shipyard_api/client.py
shipyard_api/errors.py
shipyard_api-0.3.0.dist-info/METADATA
shipyard_api-0.3.0.dist-info/WHEEL
shipyard_api-0.3.0.dist-info/RECORD
